google_authz_client/__init__.py
google_authz_client/client.py
google_authz_client/config.py
google_authz_client/django.py
google_authz_client/errors.py
google_authz_client/fastapi.py
google_authz_client/flask.py
google_authz_client/models.py
google_authz_client/token.py
google_authz_client-0.7.0.dist-info/licenses/LICENSE
google_authz_client-0.7.0.dist-info/METADATA
google_authz_client-0.7.0.dist-info/WHEEL
google_authz_client-0.7.0.dist-info/top_level.txt
google_authz_client-0.7.0.dist-info/RECORD
