Metadata-Version: 2.4
Name: google-authz-client
Version: 0.7.0
Summary: Python helpers for talking to the google-authz service from popular web frameworks.
Author: google-authz team
License: Apache-2.0
Project-URL: Homepage, https://github.com/example/google-authz-client
Classifier: Development Status :: 3 - Alpha
Classifier: Intended Audience :: Developers
Classifier: License :: OSI Approved :: Apache Software License
Classifier: Programming Language :: Python
Classifier: Programming Language :: Python :: 3
Classifier: Programming Language :: Python :: 3.10
Classifier: Programming Language :: Python :: 3.11
Classifier: Programming Language :: Python :: 3.12
Classifier: Framework :: FastAPI
Classifier: Framework :: Flask
Classifier: Framework :: Django
Requires-Python: >=3.10
License-File: LICENSE
Requires-Dist: httpx>=0.25
Requires-Dist: pydantic<3,>=1.10
Requires-Dist: typing_extensions>=4.7
Provides-Extra: fastapi
Requires-Dist: fastapi>=0.95; extra == "fastapi"
Requires-Dist: starlette>=0.27; extra == "fastapi"
Provides-Extra: flask
Requires-Dist: flask>=2.3; extra == "flask"
Provides-Extra: django
Requires-Dist: django>=4.2; extra == "django"
Provides-Extra: dev
Requires-Dist: pytest>=7.4; extra == "dev"
Requires-Dist: pytest-asyncio>=0.21; extra == "dev"
Requires-Dist: httpx>=0.25; extra == "dev"
Requires-Dist: respx>=0.20.2; extra == "dev"
Requires-Dist: mypy>=1.4; extra == "dev"
Requires-Dist: ruff>=0.1.8; extra == "dev"
Dynamic: license-file
